{
  "schemaVersion": 2,
  "updatedAt": "2026-07-18T16:29:21.536Z",
  "sourceLabel": "Google Trends RSS 기반 급상승 데이터",
  "items": [
    {
      "id": "man-utd-đấu-với-wrexham",
      "rank": 1,
      "keyword": "man utd đấu với wrexham",
      "volumeLabel": "200+",
      "startedLabel": "1시간 전",
      "change": "new",
      "changeLabel": "NEW",
      "summary": "급상승 시점에 'Trực tiếp bóng đá MU - Wrexham: Nỗ lực tấn công' 관련 뉴스가 함께 포착됐어요.",
      "relatedQueries": [],
      "newsSignals": [
        "Trực tiếp bóng đá MU - Wrexham: Nỗ lực tấn công",
        "Nhận định bóng đá MU vs Wrexham, 22h00 ngày 18/7: Quỷ đỏ thắng trận",
        "Trực tiếp giao hữu bóng đá câu lạc bộ hôm nay 18/7/2026: MU, Juventus và Dortmund ra sân"
      ]
    },
    {
      "id": "폐지",
      "rank": 2,
      "keyword": "폐지",
      "volumeLabel": "1000+",
      "startedLabel": "1시간 전",
      "change": "new",
      "changeLabel": "NEW",
      "summary": "급상승 시점에 '이준우 \"고유정 전 남편 토막살해사건 잊었나...묻힐 뻔, 경찰 '쩔쩔 구멍', 검찰 보완수사로 전모\"[여의도 진검승부]' 관련 뉴스가 함께 포착됐어요.",
      "relatedQueries": [],
      "newsSignals": [
        "이준우 \"고유정 전 남편 토막살해사건 잊었나...묻힐 뻔, 경찰 '쩔쩔 구멍', 검찰 보완수사로 전모\"[여의도 진검승부]",
        "민주당 지지층서도 ‘檢 보완수사 유지해야’ 응답이 더 많아",
        "부장판사 출신 법조 원로 일갈 \"보완수사권 폐지, 與 '전대 수단' 안돼 … 헌재 '위헌' 나올 것\""
      ]
    },
    {
      "id": "멸망전",
      "rank": 3,
      "keyword": "멸망전",
      "volumeLabel": "100+",
      "startedLabel": "1시간 전",
      "change": "new",
      "changeLabel": "NEW",
      "summary": "급상승 시점에 'SOOP, '2026 리그 오브 레전드 멸망전 with 젠지' 19일 개막' 관련 뉴스가 함께 포착됐어요.",
      "relatedQueries": [],
      "newsSignals": [
        "SOOP, '2026 리그 오브 레전드 멸망전 with 젠지' 19일 개막",
        "SOOP, ‘2026 LoL 멸망전 with Gen.G’ 본선 막 오른다",
        "SOOP, LoL·철권·다트로 주말 달군다…스포츠 콘텐츠 외연 확대"
      ]
    },
    {
      "id": "일베",
      "rank": 4,
      "keyword": "일베",
      "volumeLabel": "200+",
      "startedLabel": "1시간 전",
      "change": "new",
      "changeLabel": "NEW",
      "summary": "Google Trends에서 검색량이 빠르게 늘어난 검색어로 포착됐어요.",
      "relatedQueries": [],
      "newsSignals": []
    },
    {
      "id": "2026-國際足總世界盃",
      "rank": 5,
      "keyword": "2026 國際足總世界盃",
      "volumeLabel": "100+",
      "startedLabel": "1시간 전",
      "change": "new",
      "changeLabel": "NEW",
      "summary": "급상승 시점에 '世界盃｜別毀了純粹的足球！效法美國職業運動首度推出「冠軍戒」 引爆全球球迷怒火' 관련 뉴스가 함께 포착됐어요.",
      "relatedQueries": [],
      "newsSignals": [
        "世界盃｜別毀了純粹的足球！效法美國職業運動首度推出「冠軍戒」 引爆全球球迷怒火",
        "LV客製打造世足冠軍 「專屬旅行箱」奢華亮相",
        "大玩美式風！世盃推特製冠軍指環"
      ]
    },
    {
      "id": "чемпионат-мира-по-футболу-fifa-2026",
      "rank": 6,
      "keyword": "чемпионат мира по футболу fifa 2026",
      "volumeLabel": "100+",
      "startedLabel": "1시간 전",
      "change": "new",
      "changeLabel": "NEW",
      "summary": "급상승 시점에 'Кейн – автор самого мощного результативного удара в плей-офф ЧМ-2026' 관련 뉴스가 함께 포착됐어요.",
      "relatedQueries": [],
      "newsSignals": [
        "Кейн – автор самого мощного результативного удара в плей-офф ЧМ-2026",
        "Финансовые итоги чемпионата мира по футболу: кто выиграл и кто в минусе",
        "Сколько получат игроки сборной Испании, если выиграют финал у Аргентины?"
      ]
    },
    {
      "id": "김소영",
      "rank": 7,
      "keyword": "김소영",
      "volumeLabel": "100+",
      "startedLabel": "1시간 전",
      "change": "new",
      "changeLabel": "NEW",
      "summary": "급상승 시점에 '김소영♥오상진, 아들 출산 후 첫 가족 사진 \"백일 기념\"('띵그리TV')[순간포착] - 조선비즈' 관련 뉴스가 함께 포착됐어요.",
      "relatedQueries": [],
      "newsSignals": [
        "김소영♥오상진, 아들 출산 후 첫 가족 사진 \"백일 기념\"('띵그리TV')[순간포착] - 조선비즈",
        "오상진, 둘째 子에 \"♥김소영 아침에 일어난 얼굴 닮았다\"('띵그리TV')",
        "'오상진♥' 김소영, 子 육아 현실에 당황 \"날 발로 차고 일어나\""
      ]
    },
    {
      "id": "manchester-united",
      "rank": 8,
      "keyword": "manchester united",
      "volumeLabel": "200+",
      "startedLabel": "1시간 전",
      "change": "new",
      "changeLabel": "NEW",
      "summary": "급상승 시점에 'Ederson and Manchester United: Brazilian extends Atalanta contract afte…' 관련 뉴스가 함께 포착됐어요.",
      "relatedQueries": [],
      "newsSignals": [
        "Ederson and Manchester United: Brazilian extends Atalanta contract after Old Trafford move collapses",
        "‘Signs new deal’ – Fabrizio Romano confirms bad news for Newcastle United",
        "Man United target makes decision over future after transfer stalls"
      ]
    },
    {
      "id": "토트넘",
      "rank": 9,
      "keyword": "토트넘",
      "volumeLabel": "100+",
      "startedLabel": "1시간 전",
      "change": "new",
      "changeLabel": "NEW",
      "summary": "급상승 시점에 '토트넘 잔류에 '손-케 듀오' 웃었다… \"마지막 날 멋진 결과 축하해\"' 관련 뉴스가 함께 포착됐어요.",
      "relatedQueries": [],
      "newsSignals": [
        "토트넘 잔류에 '손-케 듀오' 웃었다… \"마지막 날 멋진 결과 축하해\"",
        "'얼마나 심각하면' 토트넘 '최악의 시즌' 이유 있었네→참다못해 내부 감사 실시... '십자인대 파열만 무려 3인'",
        "[오피셜] \"토트넘, 역대 최고 풀백 영입\" 데 제르비 감독 선수단 개편 시작... 로버트슨 FA로 데려왔다"
      ]
    },
    {
      "id": "แมนย-พบ-เร-กซ-แฮม",
      "rank": 10,
      "keyword": "แมนย พบ เร กซ แฮม",
      "volumeLabel": "500+",
      "startedLabel": "2시간 전",
      "change": "new",
      "changeLabel": "NEW",
      "summary": "급상승 시점에 'เช็กชื่อ 25 แข้งแมนยูบุกฟินแลนด์! ซานโตส ลุ้นประเดิมอุ่นเร็กซ์แฮม' 관련 뉴스가 함께 포착됐어요.",
      "relatedQueries": [],
      "newsSignals": [
        "เช็กชื่อ 25 แข้งแมนยูบุกฟินแลนด์! ซานโตส ลุ้นประเดิมอุ่นเร็กซ์แฮม",
        "โปรแกรมฟุตบอลวันนี้ 18 กรกฎาคม: อังกฤษ พบ ฝรั่งเศส, เวียดนาม พบ เมียนมาร์",
        "โปรแกรมถ่ายทอดสด \"แมนยู\" ปรีซีซั่น 2026/27 ตารางอุ่นเครื่อง ล่าสุด"
      ]
    }
  ]
}
