{
  "schemaVersion": 2,
  "updatedAt": "2026-07-18T10:24:38.555Z",
  "sourceLabel": "Google Trends RSS 기반 급상승 데이터",
  "items": [
    {
      "id": "공무원시험",
      "rank": 1,
      "keyword": "공무원시험",
      "volumeLabel": "500+",
      "startedLabel": "1시간 전",
      "change": "new",
      "changeLabel": "NEW",
      "summary": "급상승 시점에 '2027 공무원시험 개편 앞두고 달리는 청년들' 관련 뉴스가 함께 포착됐어요.",
      "relatedQueries": [],
      "newsSignals": [
        "2027 공무원시험 개편 앞두고 달리는 청년들",
        "\"공시 개편, 수험생들 먼저 움직였다\"…공단기, `2027 합격 설명회` 7000명 신청",
        "공단기, 2027년 공무원 시험 개편 설명회 개최 - 조선비즈"
      ]
    },
    {
      "id": "공단기",
      "rank": 2,
      "keyword": "공단기",
      "volumeLabel": "200+",
      "startedLabel": "1시간 전",
      "change": "new",
      "changeLabel": "NEW",
      "summary": "Google Trends에서 검색량이 빠르게 늘어난 검색어로 포착됐어요.",
      "relatedQueries": [],
      "newsSignals": []
    },
    {
      "id": "오싹한-연애",
      "rank": 3,
      "keyword": "오싹한 연애",
      "volumeLabel": "200+",
      "startedLabel": "1시간 전",
      "change": "new",
      "changeLabel": "NEW",
      "summary": "급상승 시점에 ''김부장' 종영 3회 남기고 웃음 싹…박은빈 '오싹한 연애' 등판' 관련 뉴스가 함께 포착됐어요.",
      "relatedQueries": [],
      "newsSignals": [
        "'김부장' 종영 3회 남기고 웃음 싹…박은빈 '오싹한 연애' 등판",
        "귀신 보는 박은빈, 소지섭·남궁민·지성 잡을까…'오싹한 연애' D-DAY - 머니투데이",
        "'우영우' 박은빈, 주말극으로 복귀…'오싹한 연애'"
      ]
    },
    {
      "id": "선우용여",
      "rank": 4,
      "keyword": "선우용여",
      "volumeLabel": "10000+",
      "startedLabel": "1시간 전",
      "change": "new",
      "changeLabel": "NEW",
      "summary": "급상승 시점에 '선우용여, 전원주에 \"자기 멋대로…뻔뻔스러워져\"' 관련 뉴스가 함께 포착됐어요.",
      "relatedQueries": [],
      "newsSignals": [
        "선우용여, 전원주에 \"자기 멋대로…뻔뻔스러워져\"",
        "\"하루 400만원이라고?\" 전원주 '털썩'…선우용여가 쏜 호캉스 - 머니투데이",
        "'87세' 전원주, 19살 첫사랑과 입산금지구역 갔다 파출소 行 \"엄마가 팬티 검사까지\""
      ]
    },
    {
      "id": "브라이슨-디섐보",
      "rank": 5,
      "keyword": "브라이슨 디섐보",
      "volumeLabel": "200+",
      "startedLabel": "1시간 전",
      "change": "new",
      "changeLabel": "NEW",
      "summary": "급상승 시점에 '디섐보, 디오픈서 '라이 개선'으로 벌타…람은 클럽 던져 경고' 관련 뉴스가 함께 포착됐어요.",
      "relatedQueries": [],
      "newsSignals": [
        "디섐보, 디오픈서 '라이 개선'으로 벌타…람은 클럽 던져 경고",
        "심한 야유에 인신공격까지…디오픈이 못된 갤러리들에 칼 빼든 이유",
        "LIV 골프 간판 디섐보·람 디 오픈서 수난…각각 2벌타, 경고"
      ]
    },
    {
      "id": "밤하늘",
      "rank": 6,
      "keyword": "밤하늘",
      "volumeLabel": "200+",
      "startedLabel": "2시간 전",
      "change": "new",
      "changeLabel": "NEW",
      "summary": "Google Trends에서 검색량이 빠르게 늘어난 검색어로 포착됐어요.",
      "relatedQueries": [],
      "newsSignals": []
    },
    {
      "id": "kia-vs-ssg",
      "rank": 7,
      "keyword": "kia vs ssg",
      "volumeLabel": "200+",
      "startedLabel": "2시간 전",
      "change": "new",
      "changeLabel": "NEW",
      "summary": "급상승 시점에 'SSG manager Lee highlights rookie Kim's need to handle poor-condition p…' 관련 뉴스가 함께 포착됐어요.",
      "relatedQueries": [],
      "newsSignals": [
        "SSG manager Lee highlights rookie Kim's need to handle poor-condition pitching - CHOSUNBIZ",
        "SSG Landers Manager Addresses Rookie's Early Collapse",
        "[Photo] Park Si-hu follows Kim Min-jun to take mound - CHOSUNBIZ"
      ]
    },
    {
      "id": "페덱",
      "rank": 8,
      "keyword": "페덱",
      "volumeLabel": "1000+",
      "startedLabel": "2시간 전",
      "change": "new",
      "changeLabel": "NEW",
      "summary": "급상승 시점에 '\"저런 외인 처음 봐\" 의욕 충만한 ML 32승 우승청부사, 데뷔전 강민호와 호흡 맞춘다 [오!쎈 대구]' 관련 뉴스가 함께 포착됐어요.",
      "relatedQueries": [],
      "newsSignals": [
        "\"저런 외인 처음 봐\" 의욕 충만한 ML 32승 우승청부사, 데뷔전 강민호와 호흡 맞춘다 [오!쎈 대구]",
        "[사진] 페덱, 첫 등판 무실점 호투",
        "[AI프리뷰] 18일 대구 삼성-롯데전, 관심 집중되는 삼성 페덱 KBO 데뷔전"
      ]
    },
    {
      "id": "mlb",
      "rank": 9,
      "keyword": "mlb",
      "volumeLabel": "500+",
      "startedLabel": "2시간 전",
      "change": "new",
      "changeLabel": "NEW",
      "summary": "급상승 시점에 'Highlighting Orioles draft picks after Booth Jr.' 관련 뉴스가 함께 포착됐어요.",
      "relatedQueries": [],
      "newsSignals": [
        "Highlighting Orioles draft picks after Booth Jr.",
        "One Current Oriole And One Prospect Put on Notice by the MLB Draft",
        "Three Mid-South high school players taken on first day of MLB Draft"
      ]
    },
    {
      "id": "용인반도체클러스터",
      "rank": 10,
      "keyword": "용인반도체클러스터",
      "volumeLabel": "200+",
      "startedLabel": "2시간 전",
      "change": "new",
      "changeLabel": "NEW",
      "summary": "급상승 시점에 '‘직주근접’ 넘어 ‘다(多)세권’ 아파트 뜬다' 관련 뉴스가 함께 포착됐어요.",
      "relatedQueries": [],
      "newsSignals": [
        "‘직주근접’ 넘어 ‘다(多)세권’ 아파트 뜬다",
        "용인반도체클러스터 동일하이빌 파크밸리 8월 분양",
        "‘공장이 아니라 도시가 들어선다’...용인반도체클러스터 배후 주거단지 공급 본격화"
      ]
    }
  ]
}
